discordLevelingSystem/__init__.py
discordLevelingSystem/announcement.py
discordLevelingSystem/decorators.py
discordLevelingSystem/errors.py
discordLevelingSystem/leveling_system.py
discordLevelingSystem/levels_xp_needed.py
discordLevelingSystem/member_data.py
discordLevelingSystem/role_awards.py
discordLevelingSystem-1.2.1.dist-info/LICENSE
discordLevelingSystem-1.2.1.dist-info/METADATA
discordLevelingSystem-1.2.1.dist-info/WHEEL
discordLevelingSystem-1.2.1.dist-info/top_level.txt
discordLevelingSystem-1.2.1.dist-info/RECORD
