Metadata-Version: 2.1
Name: discordLevelingSystem
Version: 1.2.1
Summary: A library to implement a leveling system into a discord bot. Contains features such as XP, level, ranks, and role awards.
Author: Defxult#8269
License: MIT
Project-URL: Homepage, https://github.com/Defxult/discordLevelingSystem
Project-URL: Changelog, https://github.com/Defxult/discordLevelingSystem/blob/main/CHANGELOG.md
Keywords: database,discord,discord bot,discord.py,discord py,discord level,discord leveling,discord leveling system,level,levels,leveling,level up,level system,mee6,rank,ranking,role award,xp
Classifier: Development Status :: 5 - Production/Stable
Classifier: Programming Language :: Python :: 3
Classifier: Programming Language :: Python :: 3.8
Classifier: Programming Language :: Python :: 3.9
Classifier: Programming Language :: Python :: 3.10
Classifier: Topic :: Software Development :: Libraries
Classifier: Topic :: Software Development :: Libraries :: Python Modules
Requires-Python: >=3.8
License-File: LICENSE
Requires-Dist: discord.py (>=2.0.0)
Requires-Dist: aiosqlite (>=0.17.0)
